simplini/__init__.py
simplini/_version.py
simplini/core.py
simplini/parser.py
simplini/renderer.py
simplini-0.0.13.dist-info/licenses/LICENSE
simplini-0.0.13.dist-info/METADATA
simplini-0.0.13.dist-info/WHEEL
simplini-0.0.13.dist-info/top_level.txt
simplini-0.0.13.dist-info/RECORD
